jupseco/__init__.py
jupseco/module.py
jupseco-0.1.0.dist-info/METADATA
jupseco-0.1.0.dist-info/WHEEL
jupseco-0.1.0.dist-info/top_level.txt
jupseco-0.1.0.dist-info/RECORD
